[{"ATTACHMENTNAME":"dc8bc216-ab5c-4ab0-8a6d-c28693c93b73.pdf","NEWS_DT":"2022-10-27T16:53:58.993","QUARTER_ID":null,"CATEGORYNAME":"Company Update","HEADLINE":"Transcript of the Conference call on financial results for quarter September 30, 2022.","SCRIP_CD":511431,"AGENDA_ID":157,"NEWSSUB":"Announcement under Regulation 30 (LODR)-Earnings Call Transcript"},{"ATTACHMENTNAME":"776bedec-dcee-47d6-ad75-fef3b0cd38e5.pdf","NEWS_DT":"2022-07-08T17:04:55.393","QUARTER_ID":null,"CATEGORYNAME":"Company Update","HEADLINE":"Transcript of the Conference call on financial results for quarter June 30, 2022.","SCRIP_CD":511431,"AGENDA_ID":157,"NEWSSUB":"Announcement under Regulation 30 (LODR)-Earnings Call Transcript"}]