[{"ATTACHMENTNAME":"8ea23f7f-b1b2-40e7-8bb2-a10ba2726947.pdf","NEWS_DT":"2022-05-30T12:33:09.817","QUARTER_ID":null,"CATEGORYNAME":"Company Update","HEADLINE":"Pursuant to provisions of Regulation 30 of the SEBI (Listing Obligations and Disclosure Requirements) Regulations, 2015, we are attaching herewith the transcript of Conference Call with Analyst / Investor held on 25th May, 2022 for the Audited Financial Results for the Quarter and financial year ended 31st March, 2022.\r\n\r\nThe same is also available on the website of the Company i.e. www.sanghicement.com\r\n\r\nPlease take the same on your records.\r\n","SCRIP_CD":526521,"AGENDA_ID":157,"NEWSSUB":"Announcement under Regulation 30 (LODR)-Earnings Call Transcript"}]