[{"ATTACHMENTNAME":"c985205f-2332-4ec2-93e6-e7a07013067d.pdf","NEWS_DT":"2022-08-08T18:24:26.393","QUARTER_ID":null,"CATEGORYNAME":"Company Update","HEADLINE":"Dear Sirs, \r\n\r\nFurther to our letter dated July 29, 2022 and August 3, 2022, we enclose herewith the transcript of the Earnings Conference Call on the Q1 FY23 results of the Company, held on Wednesday, August 3, 2022.\r\n\r\nThe said transcript is also available under the Investor Meet/Call Section of the website of the Company at https://www.evereadyindia.com/investors/investor-meet-call/.\r\n\r\nThe above is for your information and record.\r\n\r\nThanking you,\r\n","SCRIP_CD":531508,"AGENDA_ID":157,"NEWSSUB":"Announcement under Regulation 30 (LODR)-Earnings Call Transcript"}]