[{"ATTACHMENTNAME":"e16149a4-3d64-422e-b320-186374af271d.pdf","NEWS_DT":"2017-08-03T17:42:52.63","QUARTER_ID":null,"CATEGORYNAME":"Company Update","HEADLINE":"Please find enclosed herewith the transcript of the 1QFY18 Results Conference Call held on July 26, 2017 at 4.00 P.M.","SCRIP_CD":532285,"AGENDA_ID":80,"NEWSSUB":"Transcript Of The 1QFY18 Results Conference Call Held On July 26, 2017 At 4.00 P.M.<BR> <BR> "},{"ATTACHMENTNAME":"142ecb75-e7dc-4a9a-aa2e-c2a4d070c9fe.pdf","NEWS_DT":"2017-05-31T17:16:12.35","QUARTER_ID":null,"CATEGORYNAME":"Company Update","HEADLINE":"The transcript of Analyst Conference Call held on 27th May, 2017 is submitted herewith","SCRIP_CD":532285,"AGENDA_ID":80,"NEWSSUB":"Transcript Of Analyst Conference Call"},{"ATTACHMENTNAME":"49f5217d-ea0a-4afe-9a4f-a107167be2ad.pdf","NEWS_DT":"2021-05-20T17:13:46.017","QUARTER_ID":null,"CATEGORYNAME":"Company Update","HEADLINE":"Please find enclosed the Transcript of the Q4FY21 Earnings Call held on 17.05.2021.","SCRIP_CD":532285,"AGENDA_ID":157,"NEWSSUB":"Announcement under Regulation 30 (LODR)-Earnings Call Transcript"}]