[{"ATTACHMENTNAME":"3622f93d-2700-4b43-8575-aa538dec30dd.pdf","NEWS_DT":"2022-11-26T16:23:35.857","QUARTER_ID":null,"CATEGORYNAME":"Company Update","HEADLINE":"Intimation of uploading of transcript of Investors Call on the Financial Results for Q4FY22","SCRIP_CD":533344,"AGENDA_ID":1,"NEWSSUB":"Intimation Of Uploading Of Transcript Of Investors Call On The Financial Results For Q4FY22 ."},{"ATTACHMENTNAME":"99aa0735-f340-4479-84dc-53093f5aefd9.pdf","NEWS_DT":"2022-06-06T16:29:10.9","QUARTER_ID":null,"CATEGORYNAME":"Company Update","HEADLINE":"Sir/ Madam,\r\n\r\n\r\nPlease find attached the transcript of the Conference call for Q3 and 9M FY 22 results held on 30th May, 2022.\r\n\r\n","SCRIP_CD":533344,"AGENDA_ID":1,"NEWSSUB":"Transcript For Q3 And 9M FY '22 Earnings Conference Call"}]