[{"ATTACHMENTNAME":"3f23a00f-7286-4bba-8c6a-7030053d65bc.pdf","NEWS_DT":"2018-09-07T19:07:47.727","QUARTER_ID":null,"CATEGORYNAME":"Company Update","HEADLINE":"Transcript of the Conference Call of Rushil Decor Limited held on September 4, 2018.","SCRIP_CD":533470,"AGENDA_ID":157,"NEWSSUB":"Announcement under Regulation 30 (LODR)-Earnings Call Transcript"},{"ATTACHMENTNAME":"b9fe2d14-23c2-4f27-ba5b-b26ceae1c207.pdf","NEWS_DT":"2021-11-11T17:12:31.513","QUARTER_ID":null,"CATEGORYNAME":"Company Update","HEADLINE":"Transcript of Q2 FY2022 Earnings Conference Call","SCRIP_CD":533470,"AGENDA_ID":157,"NEWSSUB":"Announcement under Regulation 30 (LODR)-Earnings Call Transcript"},{"ATTACHMENTNAME":"5488a827-cac1-47bf-a009-6004867221d0.pdf","NEWS_DT":"2021-09-01T10:09:10.927","QUARTER_ID":null,"CATEGORYNAME":"Company Update","HEADLINE":"Transcript of Q1 FY2022 Earnings Conference Call","SCRIP_CD":533470,"AGENDA_ID":157,"NEWSSUB":"Announcement under Regulation 30 (LODR)-Earnings Call Transcript"},{"ATTACHMENTNAME":"783c0a4c-ae0a-43cd-989e-0515605de9d4.pdf","NEWS_DT":"2022-11-17T12:09:56.58","QUARTER_ID":null,"CATEGORYNAME":"Company Update","HEADLINE":"In terms of Regulation 30 read with Schedule III of the SEBI (LODR) Regulations, 2015, submission of the transcript in respect of Conference Call held with Investors and Analysts on Thursday, 10th November, 2022 for Unaudited Financial Results for the Quarter and Half Year Ended September 30, 2022","SCRIP_CD":533470,"AGENDA_ID":157,"NEWSSUB":"Announcement under Regulation 30 (LODR)-Earnings Call Transcript"},{"ATTACHMENTNAME":"4b24d419-4db5-45eb-a16e-d0ddcddbaf5b.pdf","NEWS_DT":"2022-08-16T10:43:12.113","QUARTER_ID":null,"CATEGORYNAME":"Company Update","HEADLINE":"Earning Call Transcript in respect of Unaudited Quarterly Financial Results for the Quarter ended on June 30, 2022","SCRIP_CD":533470,"AGENDA_ID":157,"NEWSSUB":"Announcement under Regulation 30 (LODR)-Earnings Call Transcript"},{"ATTACHMENTNAME":"bb1b7505-f0d4-4222-bcb2-19fa1ea1c0ae.pdf","NEWS_DT":"2022-06-02T11:50:52.53","QUARTER_ID":null,"CATEGORYNAME":"Company Update","HEADLINE":"Announcement under Regulation 30 (LODR)-Earnings Call Transcript","SCRIP_CD":533470,"AGENDA_ID":157,"NEWSSUB":"Announcement under Regulation 30 (LODR)-Earnings Call Transcript"}]