[{"ATTACHMENTNAME":"055bfcc6-201d-4186-a695-34c4f9710115.pdf","NEWS_DT":"2017-12-05T11:50:20.077","QUARTER_ID":null,"CATEGORYNAME":"Company Update","HEADLINE":"Parag Milk Foods Limited Earnings Conference Call Transcript of Q2FY2018 ","SCRIP_CD":539889,"AGENDA_ID":157,"NEWSSUB":"Earnings Call Transcript"},{"ATTACHMENTNAME":"22a95ad4-b07f-46d1-8bbb-b4a3efb3eb39.pdf","NEWS_DT":"2018-08-13T13:37:18.37","QUARTER_ID":null,"CATEGORYNAME":"Company Update","HEADLINE":"Parag Milk Foods Limited Q1FY19 Earnings Call Transcript.","SCRIP_CD":539889,"AGENDA_ID":157,"NEWSSUB":"Announcement under Regulation 30 (LODR)-Earnings Call Transcript"},{"ATTACHMENTNAME":"c72342d0-05e8-4ab9-97a1-2d4043a739a2.pdf","NEWS_DT":"2018-05-16T09:41:40.83","QUARTER_ID":null,"CATEGORYNAME":"Company Update","HEADLINE":" Parag Milk Foods Limited Transcript of Analyst Meet Held on 11th May, 2018 ","SCRIP_CD":539889,"AGENDA_ID":157,"NEWSSUB":"Announcement under Regulation 30 (LODR)-Earnings Call Transcript"},{"ATTACHMENTNAME":"73fcc796-887b-47dd-8eaa-d77cc2bcddb0.pdf","NEWS_DT":"2019-10-31T14:55:24.96","QUARTER_ID":null,"CATEGORYNAME":"Company Update","HEADLINE":"Parag Milk Foods Limited Q2FY20 Earnings Call Transcript","SCRIP_CD":539889,"AGENDA_ID":157,"NEWSSUB":"Announcement under Regulation 30 (LODR)-Earnings Call Transcript"},{"ATTACHMENTNAME":"24995537-3665-4113-93b2-80748fe09774.pdf","NEWS_DT":"2020-02-10T15:19:52.7","QUARTER_ID":null,"CATEGORYNAME":"Company Update","HEADLINE":"Parag Milk Foods Limited Earnings Call Transcript of Q3FY2020","SCRIP_CD":539889,"AGENDA_ID":157,"NEWSSUB":"Announcement under Regulation 30 (LODR)-Earnings Call Transcript"}]