[{"ATTACHMENTNAME":"c1aabbb2-b3d5-4b68-bd5a-ea893ad80b5e.pdf","NEWS_DT":"2017-05-31T12:50:27.387","QUARTER_ID":null,"CATEGORYNAME":"Company Update","HEADLINE":"'HPL Electric and Power Limited Q4 FY2017<BR> Results Conference Call'<BR> May 23, 2017","SCRIP_CD":540136,"AGENDA_ID":80,"NEWSSUB":"Transcript Q4 FY17"},{"ATTACHMENTNAME":"37FE8F3E_ABB8_40B0_AD1F_196540391150_172803.pdf","NEWS_DT":"2017-02-11T17:28:06","QUARTER_ID":null,"CATEGORYNAME":"Company Update","HEADLINE":"HPL Electric & Power Ltd has informed BSE regarding Transcript of Conference Call with Investors / Analyst.","SCRIP_CD":540136,"AGENDA_ID":1,"NEWSSUB":"Transcript of Conference Call with Investors / Analyst"},{"ATTACHMENTNAME":"1365d6e0-f267-4da0-8c7c-022e55e324cd.pdf","NEWS_DT":"2018-08-10T16:11:40.613","QUARTER_ID":null,"CATEGORYNAME":"Company Update","HEADLINE":"Disclosure Under Regulation 30 of SEBI (Listing Obligation and Disclosure Requirements) Regulations, 2015- Transcript of Conference Call","SCRIP_CD":540136,"AGENDA_ID":157,"NEWSSUB":"Announcement under Regulation 30 (LODR)-Earnings Call Transcript"},{"ATTACHMENTNAME":"13d207c5-18f7-4c7d-a2f7-287622de787e.pdf","NEWS_DT":"2018-06-02T12:12:14.783","QUARTER_ID":null,"CATEGORYNAME":"Company Update","HEADLINE":"Transcript of Conference Call with the Investors/Analysts","SCRIP_CD":540136,"AGENDA_ID":157,"NEWSSUB":"Announcement under Regulation 30 (LODR)-Earnings Call Transcript"},{"ATTACHMENTNAME":"310de12b-eb17-40e9-ac91-e4f43260d5e4.pdf","NEWS_DT":"2019-08-26T17:26:21.683","QUARTER_ID":null,"CATEGORYNAME":"Company Update","HEADLINE":"Disclosure under Regulation 30 of SEBI Listing Regulations 2015","SCRIP_CD":540136,"AGENDA_ID":157,"NEWSSUB":"Announcement under Regulation 30 (LODR)-Earnings Call Transcript"},{"ATTACHMENTNAME":"fddf0551-44b5-48d2-bdfe-76319ae49f00.pdf","NEWS_DT":"2019-06-04T13:47:15.72","QUARTER_ID":null,"CATEGORYNAME":"Company Update","HEADLINE":"Disclosure under Regulation 30 of SEBI Listing Regulations","SCRIP_CD":540136,"AGENDA_ID":157,"NEWSSUB":"Announcement under Regulation 30 (LODR)-Earnings Call Transcript"},{"ATTACHMENTNAME":"512e2be0-671b-4c55-87b6-899286af87ff.pdf","NEWS_DT":"2019-02-23T13:12:46.76","QUARTER_ID":null,"CATEGORYNAME":"Company Update","HEADLINE":"Transcript of Conference Call","SCRIP_CD":540136,"AGENDA_ID":157,"NEWSSUB":"Announcement under Regulation 30 (LODR)-Earnings Call Transcript"},{"ATTACHMENTNAME":"f2065140-bdec-494f-825c-85d817573e67.pdf","NEWS_DT":"2020-09-25T15:59:21.21","QUARTER_ID":null,"CATEGORYNAME":"Company Update","HEADLINE":"Transcript of Conference Call","SCRIP_CD":540136,"AGENDA_ID":157,"NEWSSUB":"Announcement under Regulation 30 (LODR)-Earnings Call Transcript"},{"ATTACHMENTNAME":"1d7abd81-3cfb-41e0-88a2-0166f040a0c0.pdf","NEWS_DT":"2020-07-21T15:14:20.73","QUARTER_ID":null,"CATEGORYNAME":"Company Update","HEADLINE":"Transcript of Conference Call","SCRIP_CD":540136,"AGENDA_ID":157,"NEWSSUB":"Announcement under Regulation 30 (LODR)-Earnings Call Transcript"},{"ATTACHMENTNAME":"be079b7b-ce4a-4486-8835-921b43a4570f.pdf","NEWS_DT":"2020-03-02T12:36:11.48","QUARTER_ID":null,"CATEGORYNAME":"Company Update","HEADLINE":"Transcript of Conference Call ","SCRIP_CD":540136,"AGENDA_ID":157,"NEWSSUB":"Announcement under Regulation 30 (LODR)-Earnings Call Transcript"},{"ATTACHMENTNAME":"d0cdaaa0-4753-4289-aae3-df77d93b2335.pdf","NEWS_DT":"2021-11-29T12:58:44.14","QUARTER_ID":null,"CATEGORYNAME":"Company Update","HEADLINE":"Disclosure under Regulation 30 of SEBI(LODR)2015","SCRIP_CD":540136,"AGENDA_ID":157,"NEWSSUB":"Announcement under Regulation 30 (LODR)-Earnings Call Transcript"},{"ATTACHMENTNAME":"aaa553d5-dd5c-4edf-b697-e57cbb864036.pdf","NEWS_DT":"2021-01-21T15:19:08.963","QUARTER_ID":null,"CATEGORYNAME":"Company Update","HEADLINE":"Transcript of Conference Call","SCRIP_CD":540136,"AGENDA_ID":157,"NEWSSUB":"Announcement under Regulation 30 (LODR)-Earnings Call Transcript"},{"ATTACHMENTNAME":"47b07cf6-a1ae-4474-ae95-98df2dc96aed.pdf","NEWS_DT":"2022-11-23T11:48:17.727","QUARTER_ID":null,"CATEGORYNAME":"Company Update","HEADLINE":"Earning Call Transcript dated 17.11.2022","SCRIP_CD":540136,"AGENDA_ID":157,"NEWSSUB":"Announcement under Regulation 30 (LODR)-Earnings Call Transcript"},{"ATTACHMENTNAME":"4b06464d-35f8-45b9-9603-6d29f93554ba.pdf","NEWS_DT":"2022-08-16T12:09:03.113","QUARTER_ID":null,"CATEGORYNAME":"Company Update","HEADLINE":"Earning Call Transcript dated 10.08.2022","SCRIP_CD":540136,"AGENDA_ID":157,"NEWSSUB":"Announcement under Regulation 30 (LODR)-Earnings Call Transcript"},{"ATTACHMENTNAME":"46f9ff44-a119-4bd8-827d-26598ccb2a86.pdf","NEWS_DT":"2022-05-31T12:11:48.12","QUARTER_ID":null,"CATEGORYNAME":"Company Update","HEADLINE":"Earning Call Transcript dated 27.05.2022","SCRIP_CD":540136,"AGENDA_ID":157,"NEWSSUB":"Announcement under Regulation 30 (LODR)-Earnings Call Transcript"},{"ATTACHMENTNAME":"ed04b6fc-352b-4a48-b548-277a7f679b56.pdf","NEWS_DT":"2022-02-21T17:45:30.797","QUARTER_ID":null,"CATEGORYNAME":"Company Update","HEADLINE":"Disclosure under Regulation 30 of SEBI(LODR)2015.","SCRIP_CD":540136,"AGENDA_ID":157,"NEWSSUB":"Announcement under Regulation 30 (LODR)-Earnings Call Transcript"}]